dict/__init__.py
dict/api_client.py
dict/configuration.py
dict/rest.py
dict/api/__init__.py
dict/api/admins_api.py
dict/api/developers_api.py
dict/api/public_api.py
dict/models/__init__.py
dict/models/descriptor.py
dict/models/descriptor_value.py
dict/models/imported_item.py
dict/models/reply_imported.py
test/__init__.py
test/test_admins_api.py
test/test_descriptor.py
test/test_descriptor_value.py
test/test_developers_api.py
test/test_imported_item.py
test/test_public_api.py
test/test_reply_imported.py
sysnet_dict-1.0.0.dist-info/LICENSE
sysnet_dict-1.0.0.dist-info/METADATA
sysnet_dict-1.0.0.dist-info/WHEEL
sysnet_dict-1.0.0.dist-info/top_level.txt
sysnet_dict-1.0.0.dist-info/RECORD
